cryptocmpy/__init__.py
cryptocmpy/core.py
cryptocmpy-0.1.2.dist-info/LICENSE
cryptocmpy-0.1.2.dist-info/METADATA
cryptocmpy-0.1.2.dist-info/WHEEL
cryptocmpy-0.1.2.dist-info/top_level.txt
cryptocmpy-0.1.2.dist-info/RECORD
