Metadata-Version: 2.1
Name: cryptocmpy
Version: 0.1.2
Summary: 
Requires-Dist: requests
